mypy/chaepy.py
chaepy-0.1.0.dist-info/METADATA
chaepy-0.1.0.dist-info/WHEEL
chaepy-0.1.0.dist-info/top_level.txt
chaepy-0.1.0.dist-info/RECORD
